{
  "last_update_id": 146423240,
  "paused": false,
  "open": [],
  "closed": [
    {
      "symbol": "PIC",
      "chain": "solana",
      "address": "HyKEeQGS2eWD3QyTiEQ7v23jUPZAqE9uQM98WHRZbrrr",
      "source": "new",
      "entry_price": 0.0001841,
      "entry_time": "2026-04-23T08:04:21.216187",
      "score": 57,
      "status": "TP",
      "exit_price": 0.0002215,
      "exit_pct": 20.32,
      "exit_time": "2026-04-23T08:14:44.181508"
    },
    {
      "symbol": "PIC",
      "chain": "solana",
      "address": "HyKEeQGS2eWD3QyTiEQ7v23jUPZAqE9uQM98WHRZbrrr",
      "source": "new",
      "entry_price": 0.0002069,
      "entry_time": "2026-04-23T08:15:29.204464",
      "score": 57,
      "status": "SL",
      "peak_price": 0.0002069,
      "trailing_active": false,
      "current_pct": -32.62,
      "exit_price": 0.0001394,
      "exit_pct": -32.62,
      "exit_time": "2026-04-23T08:29:49.458290+00:00"
    },
    {
      "symbol": "BURNIE",
      "chain": "ethereum",
      "address": "0x24E599a0960f80D30a6647e4c8ce9118b7CF6B30",
      "source": "new",
      "entry_price": 1.571e-05,
      "entry_time": "2026-04-23T08:15:31.959062",
      "score": 55,
      "status": "SL",
      "peak_price": 1.656e-05,
      "trailing_active": false,
      "current_pct": -62.99,
      "exit_price": 5.814e-06,
      "exit_pct": -62.99,
      "exit_time": "2026-04-23T08:36:50.957079+00:00"
    },
    {
      "symbol": "GALAXY",
      "chain": "solana",
      "address": "9M8vRvAejH6bgw6mUEgJw1vPMomHQex9qj1J2nAjpump",
      "source": "boost",
      "entry_price": 0.0002112,
      "peak_price": 0.0002112,
      "trailing_active": false,
      "entry_time": "2026-04-23T08:30:31.944308+00:00",
      "score": 57,
      "status": "SL",
      "current_pct": -27.13,
      "exit_price": 0.0001539,
      "exit_pct": -27.13,
      "exit_time": "2026-04-23T09:20:16.113174+00:00"
    },
    {
      "symbol": "EDGE",
      "chain": "bsc",
      "address": "0x7927e265f60B98df89Df3D8c010519B2218DD6ba",
      "source": "new",
      "entry_price": 2.59,
      "peak_price": 4.29,
      "trailing_active": true,
      "entry_time": "2026-04-23T09:15:29.672046+00:00",
      "score": 81,
      "status": "HARD_TP",
      "current_pct": 65.64,
      "exit_price": 4.29,
      "exit_pct": 65.64,
      "exit_time": "2026-04-23T09:50:18.381435+00:00"
    },
    {
      "symbol": "PORINGMAN",
      "chain": "solana",
      "address": "G46yT2JNvWWvBi4AdrcmK1viwMT2eYoCrPE8T87tpump",
      "source": "new",
      "entry_price": 0.0001389,
      "peak_price": 0.0001389,
      "trailing_active": false,
      "entry_time": "2026-04-23T12:34:52.735778+00:00",
      "score": 48,
      "status": "SL",
      "api_failures": 0,
      "current_pct": -40.13,
      "exit_price": 8.316e-05,
      "exit_pct": -40.13,
      "exit_time": "2026-04-23T12:45:10.560693+00:00"
    },
    {
      "symbol": "ANON",
      "chain": "solana",
      "address": "Bs4QR1nQMc6s5XL93RL9wuDCV5vKAtFbtA4KVT2pump",
      "source": "new",
      "entry_price": 0.0002534,
      "peak_price": 0.0004917,
      "trailing_active": true,
      "entry_time": "2026-04-23T12:34:56.106432+00:00",
      "score": 38,
      "status": "HARD_TP",
      "api_failures": 0,
      "current_pct": 94.04,
      "exit_price": 0.0004917,
      "exit_pct": 94.04,
      "exit_time": "2026-04-23T12:50:14.036258+00:00"
    },
    {
      "symbol": "KIZUNA",
      "chain": "solana",
      "address": "46QoLxoNJwhf1ssKQXBb6ZYLf1aL3XYJC2ZzjATNpump",
      "source": "new",
      "entry_price": 0.0001267,
      "peak_price": 0.000155,
      "trailing_active": false,
      "entry_time": "2026-04-23T15:01:26.315706+00:00",
      "score": 68,
      "status": "SL",
      "api_failures": 0,
      "current_pct": -36.86,
      "exit_price": 8e-05,
      "exit_pct": -36.86,
      "exit_time": "2026-04-23T18:02:54.792419+00:00"
    },
    {
      "symbol": "AIB",
      "chain": "solana",
      "address": "EjPkXfv9A9h84Dx6Wb4UFZaQzCocLKem5qdVBjCMpump",
      "source": "new",
      "entry_price": 0.0001193,
      "peak_price": 0.0001193,
      "trailing_active": false,
      "entry_time": "2026-04-23T22:30:52.129661+00:00",
      "score": 68,
      "status": "SL",
      "api_failures": 0,
      "current_pct": -34.71,
      "exit_price": 7.789e-05,
      "exit_pct": -34.71,
      "exit_time": "2026-04-23T22:33:11.177600+00:00"
    },
    {
      "symbol": "AINI",
      "chain": "solana",
      "address": "222ctdtoVgjWfLFMZLVXkj1pWFDBhYFPzzewFqLypump",
      "source": "new",
      "entry_price": 0.0007918,
      "peak_price": 0.001372,
      "trailing_active": true,
      "entry_time": "2026-04-23T22:33:47.384593+00:00",
      "score": 65,
      "status": "HARD_TP",
      "api_failures": 0,
      "current_pct": 73.28,
      "exit_price": 0.001372,
      "exit_pct": 73.28,
      "exit_time": "2026-04-23T22:55:09.221765+00:00"
    },
    {
      "symbol": "MPGA",
      "chain": "solana",
      "address": "418ibYK7mKkvMYYd2ceravMyaZpE76e2TvNwhGPCpump",
      "source": "new",
      "entry_price": 0.0001427,
      "peak_price": 0.00019,
      "trailing_active": false,
      "entry_time": "2026-04-23T23:30:52.981921+00:00",
      "score": 66,
      "status": "SL",
      "api_failures": 0,
      "current_pct": -16.54,
      "exit_price": 0.0001191,
      "exit_pct": -16.54,
      "exit_time": "2026-04-24T00:55:10.420738+00:00"
    },
    {
      "symbol": "BLACKASTER",
      "chain": "solana",
      "address": "E4C6Gbh57r3wyzTwCre3cBNUHekNihKvttQKHy78pump",
      "source": "boost",
      "entry_price": 0.0002198,
      "peak_price": 0.0002198,
      "trailing_active": false,
      "entry_time": "2026-04-24T10:00:51.615098+00:00",
      "score": 69,
      "status": "SL",
      "api_failures": 0,
      "current_pct": -16.01,
      "exit_price": 0.0001846,
      "exit_pct": -16.01,
      "exit_time": "2026-04-24T10:15:11.035916+00:00"
    },
    {
      "symbol": "GEORGE",
      "chain": "ethereum",
      "address": "0x5923873c729c875Ab1f3cf404B6C23723076E4Db",
      "source": "new",
      "entry_price": 0.00018,
      "peak_price": 0.00018,
      "trailing_active": false,
      "entry_time": "2026-04-24T11:00:54.037151+00:00",
      "score": 68,
      "status": "SL",
      "api_failures": 0,
      "current_pct": -23.83,
      "exit_price": 0.0001371,
      "exit_pct": -23.83,
      "exit_time": "2026-04-24T11:25:12.735807+00:00"
    },
    {
      "symbol": "ERC",
      "chain": "ethereum",
      "address": "0x3f9cF94fF7C43f9a30788EE85e65BcFBd71B8669",
      "source": "new",
      "entry_price": 3.984e-06,
      "peak_price": 7.908e-06,
      "trailing_active": true,
      "entry_time": "2026-04-25T01:00:47.856915+00:00",
      "score": 66,
      "status": "HARD_TP",
      "api_failures": 0,
      "current_pct": 98.49,
      "exit_price": 7.908e-06,
      "exit_pct": 98.49,
      "exit_time": "2026-04-25T01:30:12.202070+00:00"
    },
    {
      "symbol": "MULANIA",
      "chain": "solana",
      "address": "5PDD6dQwLu7Lmo2XXz7UXDuztv5wPvG8yL3oQFQpump",
      "source": "new",
      "entry_price": 0.0001119,
      "peak_price": 0.0001285,
      "trailing_active": false,
      "entry_time": "2026-04-25T03:00:50.192412+00:00",
      "score": 67,
      "status": "SL",
      "api_failures": 0,
      "current_pct": -19.8,
      "exit_price": 8.974e-05,
      "exit_pct": -19.8,
      "exit_time": "2026-04-25T04:10:12.557597+00:00"
    },
    {
      "symbol": "JAPANUNC",
      "chain": "solana",
      "address": "8FiJz3Tb39LRQQdTcB9DNpwmSoXXu8DvofCjGV8pump",
      "source": "new",
      "entry_price": 0.0001364,
      "peak_price": 0.0001364,
      "trailing_active": false,
      "entry_time": "2026-04-25T07:50:07.163724+00:00",
      "score": 66,
      "status": "SL",
      "api_failures": 0,
      "current_pct": -80.89,
      "exit_price": 2.606e-05,
      "exit_pct": -80.89,
      "exit_time": "2026-04-25T07:55:10.780153+00:00"
    },
    {
      "symbol": "ASSHOLES",
      "chain": "solana",
      "address": "8L4WsvTjiquWBXL85q5HXJHU35DDXu5PEqobsWhJpump",
      "source": "new",
      "entry_price": 0.0001212,
      "peak_price": 0.0001212,
      "trailing_active": false,
      "entry_time": "2026-04-25T13:00:51.241780+00:00",
      "score": 71,
      "status": "SL",
      "api_failures": 0,
      "current_pct": -97.39,
      "exit_price": 3.168e-06,
      "exit_pct": -97.39,
      "exit_time": "2026-04-25T13:15:12.437807+00:00"
    },
    {
      "symbol": "Sotashi",
      "chain": "solana",
      "address": "28JSdoZcfPJmnVTsxWVBQKmjhE1AFprsb68ntLbxpump",
      "source": "new",
      "entry_price": 0.0001016,
      "peak_price": 0.0001016,
      "trailing_active": false,
      "entry_time": "2026-04-25T13:30:50.091841+00:00",
      "score": 65,
      "status": "SL",
      "api_failures": 0,
      "current_pct": -97.79,
      "exit_price": 2.242e-06,
      "exit_pct": -97.79,
      "exit_time": "2026-04-25T13:50:09.062212+00:00"
    },
    {
      "symbol": "ASTERDOGE",
      "chain": "solana",
      "address": "4cdEkw5fGe2TioZ6ECgEFSiwpvBjA97CeUsQTXQGpump",
      "source": "new",
      "entry_price": 0.0001053,
      "peak_price": 0.0001298,
      "trailing_active": false,
      "entry_time": "2026-04-25T13:57:16.929561+00:00",
      "score": 72,
      "status": "SL",
      "api_failures": 0,
      "current_pct": -97.85,
      "exit_price": 2.267e-06,
      "exit_pct": -97.85,
      "exit_time": "2026-04-25T14:35:10.484744+00:00"
    },
    {
      "symbol": "UFD",
      "chain": "solana",
      "address": "66xqcY5ePzhNqNgYhovYDPNLmZMUrMdUmQBARSXopump",
      "source": "new",
      "entry_price": 0.0001517,
      "peak_price": 0.0001517,
      "trailing_active": false,
      "entry_time": "2026-04-25T15:30:53.687203+00:00",
      "score": 68,
      "status": "SL",
      "api_failures": 0,
      "current_pct": -61.92,
      "exit_price": 5.776e-05,
      "exit_pct": -61.92,
      "exit_time": "2026-04-25T15:40:11.009422+00:00"
    },
    {
      "symbol": "America is Back",
      "chain": "bsc",
      "address": "0x621efB83227F29657389724f877494f4Dc8B4444",
      "source": "new",
      "entry_price": 0.0001331,
      "peak_price": 0.0001652,
      "trailing_active": false,
      "entry_time": "2026-04-26T00:30:45.861526+00:00",
      "score": 68,
      "status": "SL",
      "api_failures": 0,
      "current_pct": -20.44,
      "exit_price": 0.0001059,
      "exit_pct": -20.44,
      "exit_time": "2026-04-26T09:10:11.941609+00:00"
    },
    {
      "symbol": "TROLLP",
      "chain": "solana",
      "address": "CDvLofmCutN2qgJXUYYVFqpdr1L8Fdp87N4CbfY9pump",
      "source": "boost",
      "entry_price": 0.0001264,
      "peak_price": 0.000208,
      "trailing_active": true,
      "entry_time": "2026-04-26T16:30:52.486753+00:00",
      "score": 79,
      "status": "HARD_TP",
      "api_failures": 0,
      "current_pct": 64.56,
      "exit_price": 0.000208,
      "exit_pct": 64.56,
      "exit_time": "2026-04-26T17:20:10.971393+00:00"
    },
    {
      "symbol": "p",
      "chain": "ethereum",
      "address": "0x29a74650310AeBC93749D7196E7e6FC01d379E9e",
      "source": "boost",
      "entry_price": 8.996e-10,
      "peak_price": 1.026e-09,
      "trailing_active": false,
      "entry_time": "2026-04-26T19:25:52.989396+00:00",
      "score": 84,
      "status": "SL",
      "api_failures": 0,
      "current_pct": -16.92,
      "exit_price": 7.474e-10,
      "exit_pct": -16.92,
      "exit_time": "2026-04-26T21:00:13.892746+00:00"
    },
    {
      "symbol": "SHIBA",
      "chain": "ethereum",
      "address": "0x969626767b9ecBB2eb20727787C5b55EB08FE696",
      "source": "boost",
      "entry_price": 1.604e-10,
      "peak_price": 2.652e-10,
      "trailing_active": true,
      "entry_time": "2026-04-26T21:00:52.129081+00:00",
      "score": 67,
      "status": "HARD_TP",
      "api_failures": 0,
      "current_pct": 65.34,
      "exit_price": 2.652e-10,
      "exit_pct": 65.34,
      "exit_time": "2026-04-26T23:05:10.206199+00:00"
    },
    {
      "symbol": "\u9f99\u867e\u521b\u59cb\u4eba\u6700\u65b0\u5e94\u7528\u9e1f\u867e",
      "chain": "bsc",
      "address": "0x741dF542F6C17EBD6c1Beb2dfc22C9c96e0D4444",
      "source": "new",
      "entry_price": 0.0002972,
      "peak_price": 0.0002972,
      "trailing_active": false,
      "entry_time": "2026-04-27T09:13:19.264259+00:00",
      "score": 67,
      "status": "SL",
      "api_failures": 0,
      "current_pct": -17.03,
      "exit_price": 0.0002466,
      "exit_pct": -17.03,
      "exit_time": "2026-04-27T09:15:13.978084+00:00"
    },
    {
      "symbol": "GWEI",
      "chain": "ethereum",
      "address": "0xEFD660d6fDB9A157A3F6f4d9892af2FCDE081ad2",
      "source": "new",
      "entry_price": 7.89,
      "peak_price": 7.89,
      "trailing_active": false,
      "entry_time": "2026-04-27T19:00:59.433055+00:00",
      "score": 67,
      "status": "SL",
      "api_failures": 0,
      "current_pct": -24.46,
      "exit_price": 5.96,
      "exit_pct": -24.46,
      "exit_time": "2026-04-27T19:10:13.384690+00:00"
    },
    {
      "symbol": "SCAM",
      "chain": "bsc",
      "address": "0x3af004d4f591eaFe1b0A7b16539fDa7B6BC64444",
      "source": "new",
      "entry_price": 0.0001131,
      "peak_price": 0.0001484,
      "trailing_active": true,
      "entry_time": "2026-04-27T18:30:52.916248+00:00",
      "score": 68,
      "status": "TSL",
      "api_failures": 0,
      "current_pct": 15.83,
      "exit_price": 0.000131,
      "exit_pct": 15.83,
      "exit_time": "2026-04-27T21:10:14.637170+00:00"
    },
    {
      "symbol": "SES",
      "chain": "solana",
      "address": "59Ntdzm81rWKBshmuhJmuPFzczUy5e4zow2NNrpcDXTy",
      "source": "boost",
      "entry_price": 0.0006304,
      "peak_price": 0.0006909,
      "trailing_active": false,
      "entry_time": "2026-04-27T21:00:54.589710+00:00",
      "score": 66,
      "status": "SL",
      "api_failures": 0,
      "current_pct": -17.88,
      "exit_price": 0.0005177,
      "exit_pct": -17.88,
      "exit_time": "2026-04-28T00:25:10.564612+00:00"
    },
    {
      "symbol": "BEEKEEPER",
      "chain": "solana",
      "address": "7mJ4tTSsL63fa69qkdDbw4fhx6SPzfA8uS4bVisStfi4",
      "source": "new",
      "entry_price": 0.0003102,
      "peak_price": 0.0003102,
      "trailing_active": false,
      "entry_time": "2026-04-28T17:31:01.565752+00:00",
      "score": 68,
      "status": "SL",
      "api_failures": 0,
      "current_pct": -19.41,
      "exit_price": 0.00025,
      "exit_pct": -19.41,
      "exit_time": "2026-04-28T17:50:13.191931+00:00"
    },
    {
      "symbol": "FAX",
      "chain": "solana",
      "address": "6rv8RwPcKGjRGyiGviPqERmYnE1XLQRMm8B7BRAvbrrr",
      "source": "new",
      "entry_price": 0.0004006,
      "peak_price": 0.0004006,
      "trailing_active": false,
      "entry_time": "2026-04-28T18:12:59.591829+00:00",
      "score": 68,
      "status": "SL",
      "api_failures": 0,
      "current_pct": -38.27,
      "exit_price": 0.0002473,
      "exit_pct": -38.27,
      "exit_time": "2026-04-28T18:15:10.986850+00:00"
    },
    {
      "symbol": "LOKI",
      "chain": "ethereum",
      "address": "0xFEeDf398124AAfeB6a36351C924bd00a361ea89A",
      "source": "new",
      "entry_price": 0.01178,
      "peak_price": 0.01178,
      "trailing_active": false,
      "entry_time": "2026-04-28T18:31:05.848388+00:00",
      "score": 67,
      "status": "SL",
      "api_failures": 0,
      "current_pct": -22.16,
      "exit_price": 0.00917,
      "exit_pct": -22.16,
      "exit_time": "2026-04-28T19:25:13.102043+00:00"
    },
    {
      "symbol": "GUMMY",
      "chain": "ethereum",
      "address": "0x3c8daa4bb8f1F0E87F581334c8eA2370D50daD5C",
      "source": "new",
      "entry_price": 3.021e-06,
      "peak_price": 3.021e-06,
      "trailing_active": false,
      "entry_time": "2026-04-28T22:29:40.650266+00:00",
      "score": 66,
      "status": "SL",
      "api_failures": 0,
      "current_pct": -20.23,
      "exit_price": 2.41e-06,
      "exit_pct": -20.23,
      "exit_time": "2026-04-28T22:30:13.877853+00:00"
    },
    {
      "symbol": "PRX",
      "chain": "solana",
      "address": "9iR8Urs95yLeiajX3T6eYK9t4YBcLbrWS8pCKgoPFb7n",
      "source": "new",
      "entry_price": 0.0003562,
      "peak_price": 0.0004379,
      "trailing_active": false,
      "entry_time": "2026-04-29T06:30:55.895641+00:00",
      "score": 65,
      "status": "SL",
      "api_failures": 0,
      "current_pct": -15.36,
      "exit_price": 0.0003015,
      "exit_pct": -15.36,
      "exit_time": "2026-04-29T07:20:13.268986+00:00"
    },
    {
      "symbol": "SIR",
      "chain": "solana",
      "address": "8N6r3NijiVY6m3V1rU9PnKt9S6CKaiEhQgd67eRdpump",
      "source": "new",
      "entry_price": 0.0001417,
      "peak_price": 0.0002307,
      "trailing_active": true,
      "entry_time": "2026-04-29T15:32:14.776177+00:00",
      "score": 68,
      "status": "HARD_TP",
      "api_failures": 0,
      "current_pct": 62.81,
      "exit_price": 0.0002307,
      "exit_pct": 62.81,
      "exit_time": "2026-04-29T15:45:20.182739+00:00"
    },
    {
      "symbol": "HOUSTON",
      "chain": "solana",
      "address": "EXrPSgaWtDDvFdHicFCJTDLiqiahpxea46QDWc4Efomo",
      "source": "new",
      "entry_price": 0.0003627,
      "peak_price": 0.0003627,
      "trailing_active": false,
      "entry_time": "2026-04-29T16:30:53.687344+00:00",
      "score": 67,
      "status": "SL",
      "api_failures": 0,
      "current_pct": -64.98,
      "exit_price": 0.000127,
      "exit_pct": -64.98,
      "exit_time": "2026-04-29T16:50:18.594523+00:00"
    },
    {
      "symbol": "FOMO",
      "chain": "solana",
      "address": "AfRt2PjEa3W3htn4imati1LXnGZxgFPjUxaq7JxYfomo",
      "source": "new",
      "entry_price": 0.000105,
      "peak_price": 0.000105,
      "trailing_active": false,
      "entry_time": "2026-04-29T17:01:20.826299+00:00",
      "score": 68,
      "status": "SL",
      "api_failures": 0,
      "current_pct": -62.99,
      "exit_price": 3.886e-05,
      "exit_pct": -62.99,
      "exit_time": "2026-04-29T17:10:13.407884+00:00"
    },
    {
      "symbol": "FOMO",
      "chain": "solana",
      "address": "Giyje4aFsU8MRwJx94j1ntwdsCT39Wxb4FgqmtAtpump",
      "source": "new",
      "entry_price": 0.0001714,
      "peak_price": 0.0001714,
      "trailing_active": false,
      "entry_time": "2026-04-29T17:15:44.537951+00:00",
      "score": 76,
      "status": "SL",
      "api_failures": 0,
      "current_pct": -64.42,
      "exit_price": 6.099e-05,
      "exit_pct": -64.42,
      "exit_time": "2026-04-29T17:20:12.779111+00:00"
    },
    {
      "symbol": "homo",
      "chain": "solana",
      "address": "J3S8XQjhwzc8MdNag9DRwkdC7xRTgqJCGxPcTR9Lpump",
      "source": "new",
      "entry_price": 0.0001493,
      "peak_price": 0.0001493,
      "trailing_active": false,
      "entry_time": "2026-04-29T18:01:05.718802+00:00",
      "score": 68,
      "status": "SL",
      "api_failures": 0,
      "current_pct": -31.82,
      "exit_price": 0.0001018,
      "exit_pct": -31.82,
      "exit_time": "2026-04-29T18:10:21.623568+00:00"
    },
    {
      "symbol": "STJUDE",
      "chain": "solana",
      "address": "E8syR4zsgQG2zo9YyiyfX4ujubByR4z6qj9stjASpump",
      "source": "new",
      "entry_price": 0.0006644,
      "peak_price": 0.0006644,
      "trailing_active": false,
      "entry_time": "2026-04-29T18:30:52.831122+00:00",
      "score": 72,
      "status": "SL",
      "api_failures": 0,
      "current_pct": -16.26,
      "exit_price": 0.0005564,
      "exit_pct": -16.26,
      "exit_time": "2026-04-29T18:35:13.399374+00:00"
    },
    {
      "symbol": "PUP",
      "chain": "solana",
      "address": "HrMp2mmpyDZJ65Mspzib7NJPXeZe2cvY5stfHG9nhWTH",
      "source": "new",
      "entry_price": 8.943e-05,
      "peak_price": 0.00017,
      "trailing_active": true,
      "entry_time": "2026-04-29T18:31:03.290096+00:00",
      "score": 68,
      "status": "HARD_TP",
      "api_failures": 0,
      "current_pct": 90.09,
      "exit_price": 0.00017,
      "exit_pct": 90.09,
      "exit_time": "2026-04-29T18:35:14.717881+00:00"
    },
    {
      "symbol": "Amureca",
      "chain": "solana",
      "address": "Ez7kt6vmS8Sym6sHmts6mQncxvxNe4kbba9ejHEnpump",
      "source": "boost",
      "entry_price": 9.411e-05,
      "peak_price": 9.849e-05,
      "trailing_active": false,
      "entry_time": "2026-04-30T00:00:58.858779+00:00",
      "score": 80,
      "status": "SL",
      "api_failures": 0,
      "current_pct": -16.17,
      "exit_price": 7.889e-05,
      "exit_pct": -16.17,
      "exit_time": "2026-04-30T00:35:09.400391+00:00"
    },
    {
      "symbol": "agentic money",
      "chain": "bsc",
      "address": "0xDf0F56cE8773A5C4f27cFaACc2D4Db482ce54444",
      "source": "new",
      "entry_price": 5.112e-05,
      "peak_price": 8.354e-05,
      "trailing_active": true,
      "entry_time": "2026-04-30T10:30:57.881609+00:00",
      "score": 72,
      "status": "HARD_TP",
      "api_failures": 0,
      "current_pct": 63.42,
      "exit_price": 8.354e-05,
      "exit_pct": 63.42,
      "exit_time": "2026-04-30T12:20:14.963558+00:00"
    },
    {
      "symbol": "SCRIBBLE",
      "chain": "solana",
      "address": "33xDbZM2bUHF841LKJauRZFrDtBJiUKhCH5yVh2KDWH2",
      "source": "new",
      "entry_price": 0.0001619,
      "peak_price": 0.000287,
      "trailing_active": true,
      "entry_time": "2026-04-30T20:49:34.768401+00:00",
      "score": 68,
      "status": "HARD_TP",
      "api_failures": 0,
      "current_pct": 77.27,
      "exit_price": 0.000287,
      "exit_pct": 77.27,
      "exit_time": "2026-04-30T20:55:18.681980+00:00"
    },
    {
      "symbol": "CHADLON",
      "chain": "solana",
      "address": "hLokvfUnqYUztoVdA4gwZnpvTKsPNefkdn2DyxGpump",
      "source": "new",
      "entry_price": 0.0001531,
      "peak_price": 0.0001531,
      "trailing_active": false,
      "entry_time": "2026-05-01T05:00:54.194874+00:00",
      "score": 68,
      "status": "SL",
      "api_failures": 0,
      "current_pct": -17.57,
      "exit_price": 0.0001262,
      "exit_pct": -17.57,
      "exit_time": "2026-05-01T05:10:09.665949+00:00"
    },
    {
      "symbol": "PETS",
      "chain": "solana",
      "address": "3QQQxazHaMb72d7N9iftT26vuk6A4Re31fYmkwA2pump",
      "source": "new",
      "entry_price": 0.0002012,
      "peak_price": 0.0003347,
      "trailing_active": true,
      "entry_time": "2026-05-01T18:30:52.331472+00:00",
      "score": 68,
      "status": "HARD_TP",
      "api_failures": 0,
      "current_pct": 66.35,
      "exit_price": 0.0003347,
      "exit_pct": 66.35,
      "exit_time": "2026-05-01T19:05:15.994739+00:00"
    },
    {
      "symbol": "Glim",
      "chain": "solana",
      "address": "Aa3MbWqcXCHw3CDXGcxsPKYkcxJwjaXfKyxsUDYaJN3P",
      "source": "new",
      "entry_price": 0.0002508,
      "peak_price": 0.0002923,
      "trailing_active": false,
      "entry_time": "2026-05-01T18:56:12.020991+00:00",
      "score": 68,
      "status": "SL",
      "api_failures": 0,
      "current_pct": -21.85,
      "exit_price": 0.000196,
      "exit_pct": -21.85,
      "exit_time": "2026-05-01T19:05:16.709842+00:00"
    },
    {
      "symbol": "UNIPUMP",
      "chain": "solana",
      "address": "9KrdYnHHrsWYpWMxyzbmmrjcXRr7ERWpB3byNeb1pump",
      "source": "new",
      "entry_price": 0.0001641,
      "peak_price": 0.0001836,
      "trailing_active": false,
      "entry_time": "2026-05-01T19:01:21.400836+00:00",
      "score": 68,
      "status": "SL",
      "api_failures": 0,
      "current_pct": -28.09,
      "exit_price": 0.000118,
      "exit_pct": -28.09,
      "exit_time": "2026-05-01T19:10:16.617303+00:00"
    },
    {
      "symbol": "NIB",
      "chain": "solana",
      "address": "8m9ska6uPw1xoFskyAWKaHnVqobC37F1okjve6L5pump",
      "source": "new",
      "entry_price": 0.0001082,
      "peak_price": 0.000141,
      "trailing_active": false,
      "entry_time": "2026-05-01T18:56:13.668070+00:00",
      "score": 68,
      "status": "SL",
      "api_failures": 0,
      "current_pct": -26.54,
      "exit_price": 7.948e-05,
      "exit_pct": -26.54,
      "exit_time": "2026-05-01T19:20:16.881297+00:00"
    },
    {
      "symbol": "\u81ea\u5df1",
      "chain": "bsc",
      "address": "0xd1f1a93eD587993E8a9573529E68d8C6Df2f4444",
      "source": "new",
      "entry_price": 0.0001093,
      "peak_price": 0.0001093,
      "trailing_active": false,
      "entry_time": "2026-05-02T07:30:56.118479+00:00",
      "score": 68,
      "status": "SL",
      "api_failures": 0,
      "current_pct": -25.61,
      "exit_price": 8.131e-05,
      "exit_pct": -25.61,
      "exit_time": "2026-05-02T07:35:11.332399+00:00"
    },
    {
      "symbol": "WINNING",
      "chain": "solana",
      "address": "JAxMg5ErnK6ji37TnUh89yA2mouDkFVpiKGaEi1mpump",
      "source": "new",
      "entry_price": 0.0003962,
      "peak_price": 0.0003962,
      "trailing_active": false,
      "entry_time": "2026-05-02T15:30:51.118748+00:00",
      "score": 72,
      "status": "SL",
      "api_failures": 0,
      "current_pct": -31.73,
      "exit_price": 0.0002705,
      "exit_pct": -31.73,
      "exit_time": "2026-05-02T15:45:11.884488+00:00"
    },
    {
      "symbol": "MOGMAN",
      "chain": "ethereum",
      "address": "0x19bfd61c945CC61468bbC3ae4cd69A282A4E4Ed4",
      "source": "new",
      "entry_price": 3.13e-05,
      "peak_price": 6.177e-05,
      "trailing_active": true,
      "entry_time": "2026-05-02T23:00:45.665344+00:00",
      "score": 67,
      "status": "HARD_TP",
      "api_failures": 0,
      "current_pct": 97.35,
      "exit_price": 6.177e-05,
      "exit_pct": 97.35,
      "exit_time": "2026-05-02T23:06:54.650314+00:00"
    },
    {
      "symbol": "Codex",
      "chain": "ethereum",
      "address": "0x5ebeE835F97d05F42fDA3B33d96414e13cD56838",
      "source": "new",
      "entry_price": 0.0003627,
      "peak_price": 0.0003627,
      "trailing_active": false,
      "entry_time": "2026-05-03T00:05:07.314140+00:00",
      "score": 67,
      "status": "SL",
      "api_failures": 0,
      "current_pct": -47.31,
      "exit_price": 0.0001911,
      "exit_pct": -47.31,
      "exit_time": "2026-05-03T00:15:11.363300+00:00"
    }
  ],
  "alerted": {
    "G46yT2JNvWWvBi4AdrcmK1viwMT2eYoCrPE8T87tpump": "2026-04-23T12:34:52.735695+00:00",
    "Bs4QR1nQMc6s5XL93RL9wuDCV5vKAtFbtA4KVT2pump": "2026-04-23T12:34:56.106338+00:00"
  },
  "holder_counts": {
    "G46yT2JNvWWvBi4AdrcmK1viwMT2eYoCrPE8T87tpump": {
      "count": 0,
      "ts": "2026-04-23T12:34:52.081564+00:00"
    },
    "Bs4QR1nQMc6s5XL93RL9wuDCV5vKAtFbtA4KVT2pump": {
      "count": 0,
      "ts": "2026-04-23T12:34:55.494479+00:00"
    }
  },
  "cooldown": {
    "G46yT2JNvWWvBi4AdrcmK1viwMT2eYoCrPE8T87tpump": "2026-04-23T12:45:10.560693+00:00",
    "Bs4QR1nQMc6s5XL93RL9wuDCV5vKAtFbtA4KVT2pump": "2026-04-23T12:50:14.036258+00:00",
    "46QoLxoNJwhf1ssKQXBb6ZYLf1aL3XYJC2ZzjATNpump": "2026-04-23T18:02:54.792419+00:00",
    "EjPkXfv9A9h84Dx6Wb4UFZaQzCocLKem5qdVBjCMpump": "2026-04-23T22:33:11.177600+00:00",
    "222ctdtoVgjWfLFMZLVXkj1pWFDBhYFPzzewFqLypump": "2026-04-23T22:55:09.221765+00:00",
    "418ibYK7mKkvMYYd2ceravMyaZpE76e2TvNwhGPCpump": "2026-04-24T00:55:10.420738+00:00",
    "E4C6Gbh57r3wyzTwCre3cBNUHekNihKvttQKHy78pump": "2026-04-24T10:15:11.035916+00:00",
    "0x5923873c729c875Ab1f3cf404B6C23723076E4Db": "2026-04-24T11:25:12.735807+00:00",
    "0x3f9cF94fF7C43f9a30788EE85e65BcFBd71B8669": "2026-04-25T01:30:12.202070+00:00",
    "5PDD6dQwLu7Lmo2XXz7UXDuztv5wPvG8yL3oQFQpump": "2026-04-25T04:10:12.557597+00:00",
    "8FiJz3Tb39LRQQdTcB9DNpwmSoXXu8DvofCjGV8pump": "2026-04-25T07:55:10.780153+00:00",
    "8L4WsvTjiquWBXL85q5HXJHU35DDXu5PEqobsWhJpump": "2026-04-25T13:15:12.437807+00:00",
    "28JSdoZcfPJmnVTsxWVBQKmjhE1AFprsb68ntLbxpump": "2026-04-25T13:50:09.062212+00:00",
    "4cdEkw5fGe2TioZ6ECgEFSiwpvBjA97CeUsQTXQGpump": "2026-04-25T14:35:10.484744+00:00",
    "66xqcY5ePzhNqNgYhovYDPNLmZMUrMdUmQBARSXopump": "2026-04-25T15:40:11.009422+00:00",
    "0x621efB83227F29657389724f877494f4Dc8B4444": "2026-04-26T09:10:11.941609+00:00",
    "CDvLofmCutN2qgJXUYYVFqpdr1L8Fdp87N4CbfY9pump": "2026-04-26T17:20:10.971393+00:00",
    "0x29a74650310AeBC93749D7196E7e6FC01d379E9e": "2026-04-26T21:00:13.892746+00:00",
    "0x969626767b9ecBB2eb20727787C5b55EB08FE696": "2026-04-26T23:05:10.206199+00:00",
    "0x741dF542F6C17EBD6c1Beb2dfc22C9c96e0D4444": "2026-04-27T09:15:13.978084+00:00",
    "0xEFD660d6fDB9A157A3F6f4d9892af2FCDE081ad2": "2026-04-27T19:10:13.384690+00:00",
    "0x3af004d4f591eaFe1b0A7b16539fDa7B6BC64444": "2026-04-27T21:10:14.637170+00:00",
    "59Ntdzm81rWKBshmuhJmuPFzczUy5e4zow2NNrpcDXTy": "2026-04-28T00:25:10.564612+00:00",
    "7mJ4tTSsL63fa69qkdDbw4fhx6SPzfA8uS4bVisStfi4": "2026-04-28T17:50:13.191931+00:00",
    "6rv8RwPcKGjRGyiGviPqERmYnE1XLQRMm8B7BRAvbrrr": "2026-04-28T18:15:10.986850+00:00",
    "0xFEeDf398124AAfeB6a36351C924bd00a361ea89A": "2026-04-28T19:25:13.102043+00:00",
    "0x3c8daa4bb8f1F0E87F581334c8eA2370D50daD5C": "2026-04-28T22:30:13.877853+00:00",
    "9iR8Urs95yLeiajX3T6eYK9t4YBcLbrWS8pCKgoPFb7n": "2026-04-29T07:20:13.268986+00:00",
    "8N6r3NijiVY6m3V1rU9PnKt9S6CKaiEhQgd67eRdpump": "2026-04-29T15:45:20.182739+00:00",
    "EXrPSgaWtDDvFdHicFCJTDLiqiahpxea46QDWc4Efomo": "2026-04-29T16:50:18.594523+00:00",
    "AfRt2PjEa3W3htn4imati1LXnGZxgFPjUxaq7JxYfomo": "2026-04-29T17:10:13.407884+00:00",
    "Giyje4aFsU8MRwJx94j1ntwdsCT39Wxb4FgqmtAtpump": "2026-04-29T17:20:12.779111+00:00",
    "J3S8XQjhwzc8MdNag9DRwkdC7xRTgqJCGxPcTR9Lpump": "2026-04-29T18:10:21.623568+00:00",
    "E8syR4zsgQG2zo9YyiyfX4ujubByR4z6qj9stjASpump": "2026-04-29T18:35:13.399374+00:00",
    "HrMp2mmpyDZJ65Mspzib7NJPXeZe2cvY5stfHG9nhWTH": "2026-04-29T18:35:14.717881+00:00",
    "Ez7kt6vmS8Sym6sHmts6mQncxvxNe4kbba9ejHEnpump": "2026-04-30T00:35:09.400391+00:00",
    "0xDf0F56cE8773A5C4f27cFaACc2D4Db482ce54444": "2026-04-30T12:20:14.963558+00:00",
    "33xDbZM2bUHF841LKJauRZFrDtBJiUKhCH5yVh2KDWH2": "2026-04-30T20:55:18.681980+00:00",
    "hLokvfUnqYUztoVdA4gwZnpvTKsPNefkdn2DyxGpump": "2026-05-01T05:10:09.665949+00:00",
    "3QQQxazHaMb72d7N9iftT26vuk6A4Re31fYmkwA2pump": "2026-05-01T19:05:15.994739+00:00",
    "Aa3MbWqcXCHw3CDXGcxsPKYkcxJwjaXfKyxsUDYaJN3P": "2026-05-01T19:05:16.709842+00:00",
    "9KrdYnHHrsWYpWMxyzbmmrjcXRr7ERWpB3byNeb1pump": "2026-05-01T19:10:16.617303+00:00",
    "8m9ska6uPw1xoFskyAWKaHnVqobC37F1okjve6L5pump": "2026-05-01T19:20:16.881297+00:00",
    "0xd1f1a93eD587993E8a9573529E68d8C6Df2f4444": "2026-05-02T07:35:11.332399+00:00",
    "JAxMg5ErnK6ji37TnUh89yA2mouDkFVpiKGaEi1mpump": "2026-05-02T15:45:11.884488+00:00",
    "0x19bfd61c945CC61468bbC3ae4cd69A282A4E4Ed4": "2026-05-02T23:06:54.650314+00:00",
    "0x5ebeE835F97d05F42fDA3B33d96414e13cD56838": "2026-05-03T00:15:11.363300+00:00"
  }
}